dddentity/__init__.py
dddentity/entity.py
dddentity/py.typed
dddentity-0.1.0.dist-info/LICENSE
dddentity-0.1.0.dist-info/WHEEL
dddentity-0.1.0.dist-info/METADATA
dddentity-0.1.0.dist-info/RECORD
